pymosquitto/__init__.py
pymosquitto/aio.py
pymosquitto/bindings.py
pymosquitto/client.py
pymosquitto/constants.py
pymosquitto/helpers.py
pymosquitto-0.4.0.dist-info/licenses/LICENSE
pymosquitto-0.4.0.dist-info/METADATA
pymosquitto-0.4.0.dist-info/WHEEL
pymosquitto-0.4.0.dist-info/top_level.txt
pymosquitto-0.4.0.dist-info/RECORD
