Metadata-Version: 2.4
Name: pymosquitto
Version: 0.4.0
Summary: A lightweight Python MQTT client implemented as a thin wrapper around libmosquitto
License-Expression: MIT
Requires-Python: >=3.8
License-File: LICENSE
Dynamic: license-file
